MANIFEST.in
README.rst
setup.cfg
setup.py
BlueChips.egg-info/PKG-INFO
BlueChips.egg-info/SOURCES.txt
BlueChips.egg-info/dependency_links.txt
BlueChips.egg-info/entry_points.txt
BlueChips.egg-info/not-zip-safe
BlueChips.egg-info/paster_plugins.txt
BlueChips.egg-info/requires.txt
BlueChips.egg-info/top_level.txt
bluechips/__init__.py
bluechips/websetup.py
bluechips/config/__init__.py
bluechips/config/deployment.ini_tmpl
bluechips/config/environment.py
bluechips/config/middleware.py
bluechips/config/routing.py
bluechips/controllers/__init__.py
bluechips/controllers/error.py
bluechips/controllers/history.py
bluechips/controllers/spend.py
bluechips/controllers/status.py
bluechips/controllers/transfer.py
bluechips/controllers/user.py
bluechips/lib/__init__.py
bluechips/lib/app_globals.py
bluechips/lib/base.py
bluechips/lib/helpers.py
bluechips/lib/permissions.py
bluechips/lib/subclass.py
bluechips/lib/totals.py
bluechips/model/__init__.py
bluechips/model/expenditure.py
bluechips/model/meta.py
bluechips/model/split.py
bluechips/model/subitem.py
bluechips/model/transfer.py
bluechips/model/types.py
bluechips/model/user.py
bluechips/public/favicon.ico
bluechips/public/css/main.css
bluechips/public/css/mobile.css
bluechips/public/icons/apple-touch-startup.png
bluechips/public/icons/apple-touch.png
bluechips/public/icons/currency-small.png
bluechips/public/icons/history.png
bluechips/public/icons/spend.png
bluechips/public/icons/status.png
bluechips/public/icons/transfer.png
bluechips/public/icons/user.png
bluechips/public/js/admin.js
bluechips/public/js/calculator.js
bluechips/public/js/mobile.js
bluechips/templates/base.mako
bluechips/templates/error.mako
bluechips/templates/emails/expenditure.txt
bluechips/templates/emails/transfer.txt
bluechips/templates/history/index.mako
bluechips/templates/mobile/base.mako
bluechips/templates/mobile/error.mako
bluechips/templates/mobile/spend/index.mako
bluechips/templates/mobile/status/index.mako
bluechips/templates/mobile/transfer/index.mako
bluechips/templates/spend/delete.mako
bluechips/templates/spend/index.mako
bluechips/templates/status/index.mako
bluechips/templates/transfer/delete.mako
bluechips/templates/transfer/index.mako
bluechips/templates/user/email.mako
