Metadata-Version: 1.0
Name: BlueChips
Version: 1.0.4
Summary: BlueChips - finances for people with shared expenses
Home-page: http://github.com/ebroder/bluechips
Author: Residents of Blue Sun Corporate Headquarters
Author-email: chips@blue-sun-corp.com
License: UNKNOWN
Platform: UNKNOWN
Classifier: Development Status :: 4 - Beta
Classifier: Environment :: Web Environment
Classifier: Framework :: Pylons
Classifier: License :: OSI Approved :: GNU General Public License (GPL)
Classifier: Natural Language :: English
Classifier: Topic :: Home Automation
Classifier: Topic :: Internet :: WWW/HTTP :: WSGI :: Application
Classifier: Topic :: Office/Business :: Financial :: Accounting
